integrationhelper/__init__.py
integrationhelper/const.py
integrationhelper/logger.py
integrationhelper/registry.py
integrationhelper/throttle.py
integrationhelper/validate.py
integrationhelper/version.py
integrationhelper/webclient.py
integrationhelper-0.2.1.dist-info/LICENSE
integrationhelper-0.2.1.dist-info/METADATA
integrationhelper-0.2.1.dist-info/WHEEL
integrationhelper-0.2.1.dist-info/top_level.txt
integrationhelper-0.2.1.dist-info/RECORD
